ssh_copy_id_via/__init__.py
ssh_copy_id_via/main.py
ssh_copy_id_via-0.1.0.dist-info/METADATA
ssh_copy_id_via-0.1.0.dist-info/WHEEL
ssh_copy_id_via-0.1.0.dist-info/entry_points.txt
ssh_copy_id_via-0.1.0.dist-info/top_level.txt
ssh_copy_id_via-0.1.0.dist-info/RECORD
