Metadata-Version: 2.4
Name: ssh-copy-id-via
Version: 0.1.0
Summary: Copy SSH keys to passwordless users via another user
Author-email: "@readwithai" <talwrii@gmail.com>
License: MIT
Project-URL: Homepage, https://github.com/talwrii/ssh-copy-id-via
Project-URL: Repository, https://github.com/talwrii/ssh-copy-id-via
Project-URL: Issues, https://github.com/talwrii/ssh-copy-id-via/issues
Keywords: ssh,ssh-copy-id,administration,security,passwordless
Classifier: Development Status :: 3 - Alpha
Classifier: Intended Audience :: System Administrators
Classifier: License :: OSI Approved :: MIT License
Classifier: Programming Language :: Python :: 3
Classifier: Programming Language :: Python :: 3.8
Classifier: Programming Language :: Python :: 3.9
Classifier: Programming Language :: Python :: 3.10
Classifier: Programming Language :: Python :: 3.11
Classifier: Programming Language :: Python :: 3.12
Classifier: Operating System :: OS Independent
Classifier: Topic :: System :: Systems Administration
Classifier: Topic :: System :: Networking
Requires-Python: >=3.8
